CHANGES.rst
CONTRIBUTORS.rst
MANIFEST.in
README.rst
setup.cfg
setup.py
docs/LICENSE.GPL
docs/LICENSE.rst
docs/index.rst
src/collective/__init__.py
src/collective.disableuser.egg-info/PKG-INFO
src/collective.disableuser.egg-info/SOURCES.txt
src/collective.disableuser.egg-info/dependency_links.txt
src/collective.disableuser.egg-info/entry_points.txt
src/collective.disableuser.egg-info/namespace_packages.txt
src/collective.disableuser.egg-info/not-zip-safe
src/collective.disableuser.egg-info/requires.txt
src/collective.disableuser.egg-info/top_level.txt
src/collective/disableuser/__init__.py
src/collective/disableuser/configure.zcml
src/collective/disableuser/interfaces.py
src/collective/disableuser/setuphandlers.py
src/collective/disableuser/testing.py
src/collective/disableuser/browser/__init__.py
src/collective/disableuser/browser/configure.zcml
src/collective/disableuser/browser/overrides/.gitkeep
src/collective/disableuser/browser/static/.gitkeep
src/collective/disableuser/locales/collective.blockedusers.pot
src/collective/disableuser/locales/update.sh
src/collective/disableuser/pas/__init__.py
src/collective/disableuser/pas/add_plugin.zpt
src/collective/disableuser/pas/plugin.py
src/collective/disableuser/profiles/default/browserlayer.xml
src/collective/disableuser/profiles/default/metadata.xml
src/collective/disableuser/profiles/default/registry.xml
src/collective/disableuser/profiles/uninstall/browserlayer.xml
src/collective/disableuser/rest/__init__.py
src/collective/disableuser/rest/configure.zcml
src/collective/disableuser/tests/__init__.py
src/collective/disableuser/tests/test_setup.py