Metadata-Version: 1.1
Name: collective.disableuser
Version: 1.0a1
Summary: Blocks login for specified users
Home-page: https://pypi.python.org/pypi/collective.disableuser
Author: Roel Bruggink
Author-email: roel@jaroel.nl
License: GPL version 2
Keywords: Python Plone
Platform: UNKNOWN
Classifier: Environment :: Web Environment
Classifier: Framework :: Plone
Classifier: Framework :: Plone :: 5.0
Classifier: Programming Language :: Python
Classifier: Programming Language :: Python :: 2.7
Classifier: Operating System :: OS Independent
Classifier: License :: OSI Approved :: GNU General Public License v2 (GPLv2)
